LICENSE.md
README.md
setup.py
backwwii.egg-info/PKG-INFO
backwwii.egg-info/SOURCES.txt
backwwii.egg-info/dependency_links.txt
backwwii.egg-info/top_level.txt
httpx/__init__.py
httpx/__version__.py
httpx/_api.py
httpx/_auth.py
httpx/_client.py
httpx/_compat.py
httpx/_config.py
httpx/_content.py
httpx/_decoders.py
httpx/_exceptions.py
httpx/_main.py
httpx/_models.py
httpx/_multipart.py
httpx/_status_codes.py
httpx/_types.py
httpx/_urlparse.py
httpx/_urls.py
httpx/_utils.py
httpx/py.typed
httpx/_transports/__init__.py
httpx/_transports/asgi.py
httpx/_transports/base.py
httpx/_transports/default.py
httpx/_transports/mock.py
httpx/_transports/wsgi.py